Workbook

Sheet Parametros a actualizar
B2: PARÁMETROS DE LA SEMANA — actualizar acá, no en las hojas de modelos
B3: Fecha de actualización | C3: 46254 | D3: Sólo modificar los campos con texto azul
B5: 1. Macro y financiero
B7: Inflación esperada mensual | C7: 0.0175 | D7: Fermín: promedio 1,7-1,8%. REM jul-26 (public. 6/8): mediana 2,0% mensual puntual. Próx. REM: 4/9. https://www.bcra.gob.ar/relevamiento-expectativas-mercado-rem/ | E7: https://www.bcra.gob.ar/relevamiento-expectativas-mercado-rem/
B8: Tasa de plazo fijo (TNA) | C8: 0.19 | D8: Actualizar según tasa vigente al momento de correr el modelo. | E8: https://www.bcra.gob.ar/plazos-fijos-online/
B9: Tasa efectiva mensual PF (referencia) | C9: =(1+C8)^(1/12)-1 | D9: Se calcula sola a partir de la TNA de arriba.
B10: Tasa anual costo financiero (si hay que pedir plata) | C10: 0.25 | D10: Mismo dato que el archivo viejo (00 Sistemas de Engorde).
B12: 2. Dólar
B14: Dólar hoy (inicio) | C14: 1515 | D14: Actualizar con cotización vigente.
B15: Dólar proyectado dic-26 (REM, referencia) | C15: 1652 | D15: REM jul-26, mediana para dic-26 ($1.652/USD). | E15: https://www.bcra.gob.ar/relevamiento-expectativas-mercado-rem/
B17: 3. Precios de hacienda — históricos y de mercado hoy
B18: Fecha de compra | C18: 46113
B19: Ternero 180 kg — precio pagado en abril (histórico) | C19: 6600 | D19: Precio real pagado en abril-2026. Fuente: Entre Surcos y Corrales (invernada). NO es el precio de hoy — es el dato histórico de la compra.
B20: Meses transcurridos desde la compra (abril → hoy) | C20: =(C3-C18)/30 | D20: Se calcula solo, a partir de la fecha de actualización de arriba y la fecha de compra (abril).
B21: Ternero 180 kg — actualizado a pesos de hoy | C21: =C19*(1+C7)^C20 | D21: Precio de abril llevado a pesos de hoy con la inflación esperada mensual. Este es el valor que debe usar el modelo como costo de compra en términos reales — no el precio histórico sin actualizar. | E21: La fórmula =(1+TNA)^(1/12)-1 asume interés compuesto mensual. Un plazo fijo real a 30 días no capitaliza dentro del mes — es simple: TNA/12. La diferencia es chica a estos plazos, pero cuando lo uso para proyectar 5-7 meses hacia adelante (fila 69, =(1+TNA)^(meses/12)) sí importa
E22: Al precio de compra lo llevo hacia adelante con inflación esperada (capitalizando). Al precio de venta futuro lo traigo hacia atrás con la misma tasa (descontando)
B23: Novillito/recriado ~270 kg — precio de mercado HOY | C23: 6200 | D23: Entre Surcos y Corrales (invernada) — precio vigente de la semana. Ya está en pesos de hoy, no requiere actualización.
B24: Novillo gordo 415-440 kg — precio de mercado HOY | C24: 4600 | D24: Mercado Agroganadero de Cañuelas (consumo/gordo) — precio vigente de la semana.
B25: Novillo gordo exportación ~500 kg — precio de mercado HOY | C25: 4600 | D25: Mercado Agroganadero de Cañuelas, categoría exportación — precio vigente de la semana.
B27: 4. Gastos comerciales (%)
B29: % Gastos comerciales — compra | C29: 0.05
B30: % Gastos comerciales — venta | C30: 0.07
B32: 5. Capitalización — sobre kg ganados
B34: % para el dueño del animal | C34: 0.45 | D34: reparto sobre kilos ganados, no sobre valor.
B35: % para el engordador (capitalizador) | C35: =1-C34
B38: 6. SITUACION ACTUAL — ¿Dónde estamos?
B40: ¿Cuál camino eligió al inicio? | C40: 1 | D40: (1=Venta oct, 2=Cap, 3=Corral, 4=Pastura, 5=Recría+corral)
B41: Fecha de hoy | C41: =TODAY()
B42: Margen acumulado hasta hoy | C42: 0

Sheet Modelos
C2: MODELOS RECRÍA + ENGORDE 2026 — Ternero 180 kg (abril) → 5 caminos desde octubre
G3: 1 | H3: 2 | I3: 3 | J3: 4 | K3: 5
C4: CAMINOS (desde 270 kg, oct-2026) | G4: Venta oct. + plazo fijo | H4: Capitalización (mar) | I4: Corral liviano (feb-jun) | J4: Engorde a pastura (mar) | K4: Recría+corral propio (may)
G5: Vende en octubre a 270 kg; compara contra poner esa plata a plazo fijo. | H5: Envía a capitalizar: sale gordo en marzo 430-440 kg. Reparto 45% dueño / 55% engordador sobre kilos ganados. | I5: Entra a corral de inicio liviano a ppios de febrero: 270→415 kg, 120 días, 1,2 kg/d. | J5: Engorde a pastura propio: sale en marzo con 430-440 kg. | K5: Recría en pastura hasta febrero (400 kg) + 90 días de corral propio a 1,1 kg/d, sale en mayo con 500 kg.
C6: Categoría inicial | E6: Ternero 180 kg
C7: Fecha de compra | E7: 46113
C8: Peso inicial (compra) | D8: kg | E8: 180
C9: Precio de compra (actualizado a pesos de hoy) | D9: $/kg | E9: ='Parametros a actualizar'!$C$21
C10: % Gastos comerciales - compra | E10: ='Parametros a actualizar'!$C$29
C12: ADPV etapa (verdeo invierno) | D12: kg/d | E12: 0.7
C13: Peso a la salida (1/oct) | D13: kg | E13: 270
C14: Fecha de salida (llegada a 270 kg) | E14: 46296
C15: Duración etapa | D15: días | E15: =E14-E7
C16: Kg producidos etapa | D16: kg/cab | E16: =E13-E8
C18: Nota | E18: Ritmo de recría según lo cargado por Fermín en sus notas (verdeo de invierno). Ver también variante 0,5 kg/d si se quiere comparar.
C20: Costo de compra neto (con gastos comerciales) | D20: $/cab | E20: =E8*E9*(1+E10)
C21: Valor del animal a la salida de la etapa común | D21: kg a 270 kg
C22: (referencia — cada camino valúa este punto de partida con su propio precio de ingreso)
C24: 1. FICHA TÉCNICA
C25: Peso entrada (= salida etapa común) | D25: kg | G25: =$E$13 | H25: =$E$13 | I25: =$E$13 | J25: =$E$13 | K25: =$E$13
C26: Fecha entrada (= salida etapa común) | G26: =$E$14 | H26: =$E$14 | I26: =$E$14 | J26: =$E$14 | K26: =$E$14
C27: Peso de salida (venta) | D27: kg | G27: 270 | H27: 435 | I27: 415 | J27: 435 | K27: 500
C28: ADPV del camino | D28: kg/d | H28: 0.55 | I28: 1.2 | J28: 0.6
C29: Fecha de salida (venta) | G29: 46296 | H29: 46447 | I29: 46419 | J29: 46447 | K29: 46508
C30: Duración del camino (desde oct) | D30: días | G30: =G29-G26 | H30: =H29-H26 | I30: =I29-I26 | J30: =J29-J26 | K30: =K29-K26
C31: Kg producidos en el camino | D31: kg/cab | G31: =G27-G25 | H31: =H27-H25 | I31: =I27-I25 | J31: =J27-J25 | K31: =K27-K25
C32: % Mortandad del camino | D32: % | G32: 0 | H32: 0.01 | I32: 0.02 | J32: 0.01 | K32: 0.015
C34: 2. PRECIOS (deflactados a pesos de hoy — inflación esperada + dólar)
C35: Precio de ingreso (270 kg, oct) — pesos de hoy | D35: $/kg | G35: ='Parametros a actualizar'!$C$23 | H35: ='Parametros a actualizar'!$C$23 | I35: ='Parametros a actualizar'!$C$23 | J35: ='Parametros a actualizar'!$C$23 | K35: ='Parametros a actualizar'!$C$23
C36: Precio de venta esperado (nominal, a la fecha de salida) | D36: $/kg | G36: ='Parametros a actualizar'!$C$23 | H36: ='Parametros a actualizar'!$C$24 | I36: ='Parametros a actualizar'!$C$24 | J36: ='Parametros a actualizar'!$C$24 | K36: ='Parametros a actualizar'!$C$25
C37: Meses entre entrada y venta (para deflactar) | D37: meses | G37: =(G29-G26)/30 | H37: =(H29-H26)/30 | I37: =(I29-I26)/30 | J37: =(J29-J26)/30 | K37: =(K29-K26)/30
C38: Precio de venta deflactado a pesos de hoy | D38: $/kg | G38: =G36/(1+'Parametros a actualizar'!$C$7)^G37 | H38: =H36/(1+'Parametros a actualizar'!$C$7)^H37 | I38: =I36/(1+'Parametros a actualizar'!$C$7)^I37 | J38: =J36/(1+'Parametros a actualizar'!$C$7)^J37 | K38: =K36/(1+'Parametros a actualizar'!$C$7)^K37
C40: Camino 1 no necesita deflactar (venta el mismo día de la etapa común). Los demás traen el precio de venta futuro a pesos de hoy con la inflación esperada de Parámetros (1,7-1,8% mensual, definido por Fermín).
C42: 3. INGRESOS Y GASTOS (pesos de hoy)
C43: Ingreso bruto por venta [Camino 2: (kg entrada + 45% kg ganados) x precio venta] | D43: $/cab | G43: =G27*G38*(1-G32) | H43: =(H25+(H31*'Parametros a actualizar'!$C$34))*H38*(1-H32) | I43: =I27*I38*(1-I32) | J43: =J27*J38*(1-J32) | K43: =K27*K38*(1-K32)
C44: % Gastos comerciales - venta | D44: % | G44: ='Parametros a actualizar'!$C$30 | H44: ='Parametros a actualizar'!$C$30 | I44: ='Parametros a actualizar'!$C$30 | J44: ='Parametros a actualizar'!$C$30 | K44: ='Parametros a actualizar'!$C$30
C45: Ingreso neto de venta | D45: $/cab | G45: =G43*(1-G44) | H45: =H43*(1-H44) | I45: =I43*(1-I44) | J45: =J43*(1-J44) | K45: =K43*(1-K44)
C47: 4. COSTOS DEL CAMINO (desde oct, además del costo de compra ya incorporado en la etapa común)
C48: Costo de alimentación / recría / corral | D48: $/cab | G48: =G31*G104 | H48: =H31*H104 | I48: =I31*I104 | J48: =J31*J104 | K48: =K31*K104
C49: Sanidad | D49: $/cab | E49: 0.02 | G49: =$E$9*$E$49 | H49: =$E$9*$E$49 | I49: =$E$9*$E$49 | J49: =$E$9*$E$49 | K49: =$E$9*$E$49
C50: Gastos de estructura / personal (prorrateado) | D50: $/cab | G50: 0 | H50: 0 | I50: 25000 | J50: 15000 | K50: 20000
C51: Gastos directos totales | D51: $/cab | G51: =SUM(G48:G50) | H51: =SUM(H48:H50) | I51: =SUM(I48:I50) | J51: =SUM(J48:J50) | K51: =SUM(K48:K50)
C53: Costo de alimentación = kg producidos del camino × costo/kg ganado (ver sección 12, al final de la hoja). Sanidad y gastos de estructura siguen como valores de referencia a completar.
C55: 5. MARGEN EN PESOS DE HOY
C56: Margen bruto por cabeza | D56: $/cab | G56: =G45-G51-$E$20 | H56: =H45-H51-$E$20 | I56: =I45-I51-$E$20 | J56: =J45-J51-$E$20 | K56: =K45-K51-$E$20
C57: Capital inmovilizado (costo compra + 50% gastos directos) | D57: $/cab | G57: =$E$20+(G51*0.5) | H57: =$E$20+(H51*0.5) | I57: =$E$20+(I51*0.5) | J57: =$E$20+(J51*0.5) | K57: =$E$20+(K51*0.5)
C59: 6. MARGEN EN USD (lectura complementaria — no reemplaza la de pesos)
C60: Margen bruto por cabeza en USD | D60: USD/cab | G60: =G56/'Parametros a actualizar'!$C$14 | H60: =H56/'Parametros a actualizar'!$C$14 | I60: =I56/'Parametros a actualizar'!$C$14 | J60: =J56/'Parametros a actualizar'!$C$14 | K60: =K56/'Parametros a actualizar'!$C$14
C62: 7. COSTO FINANCIERO — si hay que salir a pedir plata
C63: Meses de capital inmovilizado (desde oct) | D63: meses | G63: =G37 | H63: =H37 | I63: =I37 | J63: =J37 | K63: =K37
C64: Costo financiero (tasa anual s/ capital inmovilizado) | D64: $/cab | G64: =G57*'Parametros a actualizar'!$C$10*G63/12 | H64: =H57*'Parametros a actualizar'!$C$10*H63/12 | I64: =I57*'Parametros a actualizar'!$C$10*I63/12 | J64: =J57*'Parametros a actualizar'!$C$10*J63/12 | K64: =K57*'Parametros a actualizar'!$C$10*K63/12
C65: Margen después de costo financiero | D65: $/cab | G65: =G56-G64 | H65: =H56-H64 | I65: =I56-I64 | J65: =J56-J64 | K65: =K56-K64
C67: 8. CONTRASTE VS. RENTA DE MERCADO — plazo fijo en pesos
C68: Capital que se inmoviliza (= costo de compra neto, etapa común) | D68: $/cab | G68: =$E$20 | H68: =$E$20 | I68: =$E$20 | J68: =$E$20 | K68: =$E$20
C69: Valor de ese capital a plazo fijo, misma fecha de salida | D69: $/cab | G69: =G68*(1+'Parametros a actualizar'!$C$8)^(G63/12) | H69: =H68*(1+'Parametros a actualizar'!$C$8)^(H63/12) | I69: =I68*(1+'Parametros a actualizar'!$C$8)^(I63/12) | J69: =J68*(1+'Parametros a actualizar'!$C$8)^(J63/12) | K69: =K68*(1+'Parametros a actualizar'!$C$8)^(K63/12)
C70: Renta del plazo fijo en el período | D70: $/cab | G70: =G69-G68 | H70: =H69-H68 | I70: =I69-I68 | J70: =J69-J68 | K70: =K69-K68
C71: Resultado del negocio vs. plazo fijo (diferencia) | D71: $/cab | G71: =G65-G70 | H71: =H65-H70 | I71: =I65-I70 | J71: =J65-J70 | K71: =K65-K70
C72: Resultado del negocio vs. plazo fijo (%) | D72: % | G72: =IFERROR(G71/G70,"") | H72: =IFERROR(H71/H70,"") | I72: =IFERROR(I71/I70,"") | J72: =IFERROR(J71/J70,"") | K72: =IFERROR(K71/K70,"")
C74: 9. PRECIO Y PRODUCCIÓN DE INDIFERENCIA
C75: Precio de indiferencia de venta | D75: $/kg | G75: =(G51+G64+$E$20)/(G27*(1-G44)*(1-G32)) | H75: =(H51+H64+$E$20)/(H27*(1-H44)*(1-H32)) | I75: =(I51+I64+$E$20)/(I27*(1-I44)*(1-I32)) | J75: =(J51+J64+$E$20)/(J27*(1-J44)*(1-J32)) | K75: =(K51+K64+$E$20)/(K27*(1-K44)*(1-K32))
C76: Producción de indiferencia (kg adicionales necesarios) | D76: kg/cab | G76: =(G51+G64+$E$20)/(G38*(1-G44)*(1-G32))-G25 | H76: =(H51+H64+$E$20)/(H38*(1-H44)*(1-H32))-H25 | I76: =(I51+I64+$E$20)/(I38*(1-I44)*(1-I32))-I25 | J76: =(J51+J64+$E$20)/(J38*(1-J44)*(1-J32))-J25 | K76: =(K51+K64+$E$20)/(K38*(1-K44)*(1-K32))-K25
C77: Nota: si la producción de indiferencia da negativa, significa que el margen ya es positivo sin necesitar más kilos (el costo de compra ya está cubierto por el precio actual) — no es un error.
C78: 10. COSTOS DIFERENCIALES ENTRE TIEMPOS DE SALIDA (vs. Camino 1 = referencia más corta)
C79: Meses adicionales respecto al Camino 1 (oct) | D79: meses | G79: =G37-$G$37 | H79: =H37-$G$37 | I79: =I37-$G$37 | J79: =J37-$G$37 | K79: =K37-$G$37
C80: Costo financiero adicional respecto al Camino 1 | D80: $/cab | G80: =G64-$G$64 | H80: =H64-$G$64 | I80: =I64-$G$64 | J80: =J64-$G$64 | K80: =K64-$G$64
C81: Renta de plazo fijo adicional (lucro cesante de esperar) | D81: $/cab | G81: =G70-$G$70 | H81: =H70-$G$70 | I81: =I70-$G$70 | J81: =J70-$G$70 | K81: =K70-$G$70
C83: 11. CUADRO RESUMEN — comparación de los 5 caminos
G84: 1 | H84: 2 | I84: 3 | J84: 4 | K84: 5
C85: Indicador | G85: Venta oct. + plazo fijo | H85: Capitalización (mar) | I85: Corral liviano (feb-jun) | J85: Engorde a pastura (mar) | K85: Recría+corral propio (may)
C86: Fecha de salida | G86: =G29 | H86: =H29 | I86: =I29 | J86: =J29 | K86: =K29
C87: Duración desde oct (días) | G87: =G30 | H87: =H30 | I87: =I30 | J87: =J30 | K87: =K30
C88: Peso de venta (kg) | G88: =G27 | H88: =H27 | I88: =I27 | J88: =J27 | K88: =K27
C89: Margen bruto ($/cab) | G89: =G56 | H89: =H56 | I89: =I56 | J89: =J56 | K89: =K56
C90: Margen bruto (USD/cab) | G90: =G60 | H90: =H60 | I90: =I60 | J90: =J60 | K90: =K60
C91: Margen dps. costo financiero ($/cab) | G91: =G65 | H91: =H65 | I91: =I65 | J91: =J65 | K91: =K65
C92: Resultado vs. plazo fijo ($/cab) | G92: =G71 | H92: =H71 | I92: =I71 | J92: =J71 | K92: =K71
C93: Resultado vs. plazo fijo (%) | G93: =G72 | H93: =H72 | I93: =I72 | J93: =J72 | K93: =K72
C94: Precio de indiferencia ($/kg) | G94: =G75 | H94: =H75 | I94: =I75 | J94: =J75 | K94: =K75
C96: Lectura sugerida: comparar 'Resultado vs. plazo fijo' entre caminos — el que más se aleje en positivo es el que mejor compensa el tiempo y riesgo adicional de esperar. Costos de alimentación de corral/pastura (fila 4) son valores de referencia a completar con el detalle real antes de cerrar el podcast.
C98: Referencias de color:
C99: Amarillo: Input editable — valores que se cargan/actualizan a mano en cada camino
C100: Verde (texto): Link a la hoja Parámetros — se actualiza solo desde ahí
C103: 12. COSTO DE ALIMENTACIÓN POR KG GANADO (apoyo — completar corriendo la dieta en el archivo '00 Sistemas de Engorde Novillo')
C104: Costo por kg ganado ($/kg) — según sistema de alimentación de cada camino | G104: 0 | H104: 0 | I104: 2000 | J104: 1000 | K104: 1500
G105: No aplica — venta directa sin engorde adicional. | H105: A cargo del capitalizador, no es costo del dueño. | I105: Corral liviano ~1,2 kg/d: correr hoja 'Corral de inicio' del archivo viejo con estos parámetros → tomar celda P18 (Costo kg ganado). | J105: Pastura propia: estimar costo de verdeo/pastura por kg producido (no hay hoja de dieta específica para pastura en el archivo viejo — cargar a mano). | K105: Recría pastura + 90d corral 1,1 kg/d: combinar costo de pastura (parte 1) + hoja 'Novillito Grano)' o 'Maiz+cp liviano' del archivo viejo para el tramo de corral (parte 2).
